ImageConverter/__init__.py
ImageConverter/cli.py
ImageConverter/converter.py
ImageConverter/version.py
ImageConverter-1.0.7.dist-info/METADATA
ImageConverter-1.0.7.dist-info/WHEEL
ImageConverter-1.0.7.dist-info/entry_points.txt
ImageConverter-1.0.7.dist-info/top_level.txt
ImageConverter-1.0.7.dist-info/RECORD
