Metadata-Version: 2.1
Name: ImageConverter
Version: 1.0.7
Summary: A python package for converting .jpg and .jpeg file formats to .png
Home-page: https://github.com/xXSD11Xx/imageconversion
Author: xXSDXx
Author-email: dailycodingpro@gmail.com
License: MIT
Keywords: image,converter,jpg,png,jpeg,jpeg to png,jpg to png
Platform: UNKNOWN
Classifier: License :: OSI Approved :: MIT License
Classifier: Programming Language :: Python :: 3
Classifier: Programming Language :: Python :: 3.7
Classifier: Programming Language :: Python :: 3.8
Requires-Dist: Pillow
